<?xml version="1.0" encoding="UTF-8" standalone="no"?>
<databaseChangeLog xmlns="http://www.liquibase.org/xml/ns/dbchangelog"
                   xmlns:xsi="http://www.w3.org/2001/XMLSchema-instance"
                   xsi:schemaLocation="http://www.liquibase.org/xml/ns/dbchangelog http://www.liquibase.org/xml/ns/dbchangelog/dbchangelog-2.0.xsd">

  <changeSet author="y.zakharov" id="1">
    <createTable tableName="waytoimproveskill">
      <column name="id" type="BIGINT">
        <constraints nullable="false"/>
      </column>
      <column name="caption" type="VARCHAR(200)">
        <constraints nullable="false"/>
      </column>
      <column name="grade" type="VARCHAR(100)">
        <constraints nullable="false"/>
      </column>
      <column name="resourceType" type="VARCHAR(100)">
        <constraints nullable="false"/>
      </column>
      <column name="link" type="VARCHAR(200)"/>
    </createTable>
    <addPrimaryKey columnNames="id" constraintName="PKUK_WayToImproveSkill" tableName="waytoimproveskill"/>
  </changeSet>
  <changeSet author="y.zakharov" id="2">
    <createTable tableName="requiredskill_waytoimproveskill">
      <column name="ways_id" type="BIGINT">
        <constraints nullable="false"/>
      </column>
      <column name="skill_id" type="BIGINT">
        <constraints nullable="false"/>
      </column>
    </createTable>
    <addForeignKeyConstraint baseColumnNames="ways_id" baseTableName="requiredskill_waytoimproveskill"
                             constraintName="FK_requiredskill_RSWTIS" referencedColumnNames="id"
                             referencedTableName="waytoimproveskill"/>
    <addForeignKeyConstraint baseColumnNames="skill_id" baseTableName="requiredskill_waytoimproveskill"
                             constraintName="FK_waytoimproveskill_RSWTIS" referencedColumnNames="id"
                             referencedTableName="requiredskill"/>
  </changeSet>
</databaseChangeLog>